./.git
./.gitignore
./.mcp.json
./CLAUDE.md
./PKG-INFO
./README.md
./pyproject.toml
./server.py
./test_integration.py
./test_milvus.py
./test_shutdown.py
./uv.lock
./.github/workflows/publish.yml
./.serena/project.yml
./.serena/cache/python/document_symbols_cache_v23-06-25.pkl
./.serena/memories/architecture_patterns.md
./.serena/memories/code_style_conventions.md
./.serena/memories/project_overview.md
./.serena/memories/suggested_commands.md
./.serena/memories/task_completion_checklist.md
mkdocs_mcp_plugin-0.4.1.dist-info/METADATA
mkdocs_mcp_plugin-0.4.1.dist-info/WHEEL
mkdocs_mcp_plugin-0.4.1.dist-info/entry_points.txt
mkdocs_mcp_plugin-0.4.1.dist-info/RECORD
