Metadata-Version: 2.4
Name: mkdocs-mcp-plugin
Version: 0.4.1
Summary: MCP server for MkDocs documentation with intelligent search and retrieval capabilities
Project-URL: Homepage, https://github.com/dongookson/mkdocs-mcp-plugin
Project-URL: Documentation, https://github.com/dongookson/mkdocs-mcp-plugin#readme
Project-URL: Repository, https://github.com/dongookson/mkdocs-mcp-plugin.git
Project-URL: Issues, https://github.com/dongookson/mkdocs-mcp-plugin/issues
Author-email: Dongook Son <d@dou.so>
License: MIT
Keywords: ai,documentation,mcp,mkdocs,rag,search
Classifier: Development Status :: 4 - Beta
Classifier: Intended Audience :: Developers
Classifier: License :: OSI Approved :: MIT License
Classifier: Programming Language :: Python :: 3
Classifier: Programming Language :: Python :: 3.12
Classifier: Topic :: Documentation
Classifier: Topic :: Software Development :: Documentation
Classifier: Topic :: Text Processing :: Markup
Requires-Python: >=3.12
Requires-Dist: fastmcp>=2.11.1
Requires-Dist: markdown>=3.8.2
Requires-Dist: mkdocs-git-revision-date-localized-plugin>=1.4.7
Requires-Dist: mkdocs-material>=9.6.16
Requires-Dist: mkdocs-mermaid2-plugin>=1.2.1
Requires-Dist: mkdocs-minify-plugin>=0.8.0
Requires-Dist: mkdocs-print-site-plugin>=2.8
Requires-Dist: nltk>=3.9.1
Requires-Dist: numpy>=2.3.2
Requires-Dist: pymdown-extensions>=10.16.1
Requires-Dist: pymilvus[model]>=2.4.0
Requires-Dist: pyyaml>=6.0.2
Requires-Dist: sentence-transformers>=5.0.0
Provides-Extra: dev
Requires-Dist: black; extra == 'dev'
Requires-Dist: mypy; extra == 'dev'
Requires-Dist: pre-commit; extra == 'dev'
Requires-Dist: pytest-cov; extra == 'dev'
Requires-Dist: pytest>=7.0; extra == 'dev'
Requires-Dist: ruff; extra == 'dev'
